{"org_id": "02600824", "org_name_cn": "上海益民商业集团股份有限公司", "org_short_name_cn": "益民集团", "org_name_en": "Shanghai Yimin Commercial Group Co.,Ltd.", "org_short_name_en": "YIMIN GROUP", "main_operation_business": "百货零售业。", "operating_scope": "　　国内贸易（除专项规定），摄影，电脑租赁，自有房屋租赁，房产销售，实业投资，自营和代理各类商品及技术的进出口业务，但国家限定公司经营或禁止进出口的商品技术外（不另附进出口商品目录），经营进料加工和“三来一补”业务，经营对销贸易和转口贸易（涉及许可经营的凭许可证经营）。", "district_encode": "310101", "org_cn_introduction": "上海益民商业集团股份有限公司主营业务是百货零售业。公司主要产品包括内衣、黄金珠宝、百货、旅游饮食服务。", "legal_representative": "陈洪志", "general_manager": "陈洪志(代)", "secretary": "朱明", "established_date": 755452800000, "reg_asset": 1054027073.0, "staff_num": 592, "telephone": "86-21-64339888", "postcode": "200020", "fax": "86-21-64721377", "email": "yimin@yimingroup.com", "org_website": "www.yimingroup.com", "reg_address_cn": "上海市黄浦区淮海中路809号甲七楼", "reg_address_en": "", "office_address_cn": "上海市黄浦区淮海中路809号甲", "office_address_en": "", "currency_encode": "019001", "currency": "CNY", "listed_date": 760291200000, "provincial_name": "上海市", "actual_controller": "上海市黄浦区国有资产监督管理委员会 (39.32%)", "classi_name": "地市国资控股", "pre_name_cn": "上海益民商业股份有限公司", "chairman": "陈洪志", "executives_nums": 15, "actual_issue_vol": 12700000.0, "issue_price": 6.6, "actual_rc_net_amt": 82320000.0, "pe_after_issuing": 15.0, "online_success_rate_of_issue": null, "affiliate_industry": {"ind_code": "BK0036", "ind_name": "服装家纺"}}