{"org_id": "T000057933", "org_name_cn": "港中旅华贸国际物流股份有限公司", "org_short_name_cn": "华贸物流", "org_name_en": "Cts International Logistics Corporation Limited", "org_short_name_en": "CTS Logistics", "main_operation_business": "国际空海铁货运代理、跨境电商物流、国际工程物流、国际仓储物流、其他国际综合物流服务，以及特大件特种专业物流。", "operating_scope": "　　许可项目，快递服务（除国内信件快递业务）；道路货物运输（不含危险货物）。（依法须经批准的项目,经相关部门批准后方可开展经营活动，具体经营项目以相关部门批准文件或许可证件为准）。一般项目，承办海运、陆运、空运进出口货物、过境货物、国际展品和私人物品的国际运输代理业务，包括：揽货、订舱、仓储、包装、中转、集装箱拼装拆箱、结算运杂费、报关、报验、相关的短途运输服务及运输咨询业务；国内航空货运销售代理业务；无船承运业务。（除依法须经批准的项目外,凭营业执照依法自主开展经营活动）。", "district_encode": "310115", "org_cn_introduction": "港中旅华贸国际物流股份有限公司主营业务为国际空海铁货运代理、跨境电商物流、国际工程物流、国际仓储物流、其他国际综合物流服务，以及特大件特种专业物流。在最近一期的中国货代物流企业百强排行榜中，综合实力第8位，国际空运业务第5位，国际海运业务第7位，公司最近10年年度排名均在行业前列。", "legal_representative": "向宏", "general_manager": "陈宇", "secretary": "于永乾", "established_date": 472838400000, "reg_asset": 1309462971.0, "staff_num": 3966, "telephone": "86-21-63588811", "postcode": "200003", "fax": "86-21-63582311", "email": "ird@ctsfreight.com", "org_website": "www.ctsfreight.com", "reg_address_cn": "上海市浦东新区浦东机场海天一路528号", "reg_address_en": "", "office_address_cn": "上海市黄浦区南京西路338号天安中心20楼", "office_address_en": "", "currency_encode": "019001", "currency": "CNY", "listed_date": 1338220800000, "provincial_name": "上海市", "actual_controller": "国务院国有资产监督管理委员会 (45.79%)", "classi_name": "央企国资控股", "pre_name_cn": null, "chairman": "向宏", "executives_nums": 11, "actual_issue_vol": 100000000.0, "issue_price": 6.66, "actual_rc_net_amt": 609820816.0, "pe_after_issuing": 27.75, "online_success_rate_of_issue": 0.50384192, "affiliate_industry": {"ind_code": "BK0052", "ind_name": "物流"}}