{"org_id": "T000122611", "org_name_cn": "顾家家居股份有限公司", "org_short_name_cn": "顾家家居", "org_name_en": "Jason Furniture(Hangzhou)Co.,Ltd", "org_short_name_en": "", "main_operation_business": "客餐厅、卧室及全屋定制家居产品的研究、开发、生产和销售。", "operating_scope": "　　沙发、床、餐桌、椅、茶几及相关零配件的设计、生产；销售：自产产品；从事上述产品及其同类产品的批发、特许经营及进出口业务，佣金代理（拍卖除外）（以上商品进出口不涉及国营贸易、进出口配额许可证、出口配额招标、出口许可证等专项管理的商品）；从事装饰材料和工艺美术品的进出口业务（以上商品进出口不涉及国营贸易、进出口配额许可证、出口配额招标、出口许可证等专项管理的商品）；企业信息咨询服务；家用电器销售；家电产品的安装、维修及售后服务。", "district_encode": "330114", "org_cn_introduction": "顾家家居股份有限公司专注于客餐厅、卧室及全屋定制家居产品的研究、开发、生产和销售。公司的主要产品是沙发、餐椅、床、配套产品、定制家具、红木家具、信息技术服务。公司荣获2020年度软体家居匠心产品奖、2020年度中国家居品牌力量榜-设计创新奖、最佳寝具（软床）金汐奖优秀奖。", "legal_representative": "顾江生", "general_manager": "李东来", "secretary": "陈邦灯", "established_date": 1162224000000, "reg_asset": 632256725.0, "staff_num": 16250, "telephone": "86-571-85016806;86-571-88603816", "postcode": "310017", "fax": "86-571-85016488", "email": "securities@kukahome.com", "org_website": "www.kukahome.com", "reg_address_cn": "浙江省杭州市钱塘区经济技术开发区11号大街113号", "reg_address_en": "", "office_address_cn": "浙江省杭州市上城区东宁路599号顾家大厦", "office_address_en": "", "currency_encode": "019001", "currency": "CNY", "listed_date": 1476374400000, "provincial_name": "浙江省", "actual_controller": "顾江生 (19.91%)，顾玉华 (8.38%)，王火仙 (5.59%)", "classi_name": "民营企业", "pre_name_cn": null, "chairman": "顾江生", "executives_nums": 15, "actual_issue_vol": 82500000.0, "issue_price": 24.66, "actual_rc_net_amt": 1956791700.0000002, "pe_after_issuing": 22.99, "online_success_rate_of_issue": 0.06470226, "affiliate_industry": {"ind_code": "BK0039", "ind_name": "家用轻工"}}