{"org_id": "T000027277", "org_name_cn": "隆基绿能科技股份有限公司", "org_short_name_cn": "隆基股份", "org_name_en": "Longi Green Energy Technology Co.,Ltd.", "org_short_name_en": "LONGi", "main_operation_business": "单晶硅棒,硅片,电池和组件的研发,生产和销售，为光伏集中式地面电站和分布式屋顶开发提供产品和系统解决方案。", "operating_scope": "　　半导体材料、太阳能电池、电子元器件、半导体设备的开发、制造、销售；商品进出口业务；光伏电站工程设计施工、光伏电站系统运行维护；LED照明灯具、节能产品的销售、维修及技术服务；合同能源管理。（以上经营范围涉及许可经营项目的，凭许可证明文件或批准证书在有效期内经营，未经许可不得经营）。", "district_encode": "610116", "org_cn_introduction": "隆基绿能科技股份有限公司主要从事单晶硅棒,硅片,电池和组件的研发,生产和销售，为光伏集中式地面电站和分布式屋顶开发提供产品和系统解决方案。公司的主要产品为太阳能组件及电池、硅片及硅棒、电站建设及服务、电力。公司是全球最大的集研发、生产、销售、服务于一体的单晶光伏产品制造企业，始终坚持以提升客户价值为核心，通过技术创新驱动提升公司的市场竞争力，多项核心技术与产品处于行业领先地位。", "legal_representative": "李振国", "general_manager": "李振国", "secretary": "刘晓东", "established_date": 950457600000, "reg_asset": 5412952708.000001, "staff_num": 46631, "telephone": "86-29-81566863;86-29-86519912", "postcode": "710018", "fax": "86-29-86689601", "email": "longi-board@longi.com", "org_website": "www.longi.com", "reg_address_cn": "陕西省西安市长安区航天中路388号", "reg_address_en": "", "office_address_cn": "陕西省西安市未央区经济技术开发区尚苑路8369号", "office_address_en": "", "currency_encode": "019001", "currency": "CNY", "listed_date": 1334073600000, "provincial_name": "陕西省", "actual_controller": "李振国 (14.08%)，李喜燕 (5.02%)", "classi_name": "民营企业", "pre_name_cn": "西安隆基硅材料股份有限公司", "chairman": "钟宝申", "executives_nums": 13, "actual_issue_vol": 75000000.0, "issue_price": 21.0, "actual_rc_net_amt": 1513105000.0, "pe_after_issuing": 24.71, "online_success_rate_of_issue": 2.08633606, "affiliate_industry": {"ind_code": "BK0020", "ind_name": "电气设备"}}