{"org_id": "T000174024", "org_name_cn": "深圳市景旺电子股份有限公司", "org_short_name_cn": "景旺电子", "org_name_en": "Shenzhen Kinwong Electronic Co.,Ltd.", "org_short_name_en": "Kinwong", "main_operation_business": "从事印制电路板的研发、生产和销售。", "operating_scope": "　　生产经营双面线路板、多层线路板、柔性线路板（法律、行政法规、国务院决定禁止的项目除外，限制的项目须取得许可后方可经营）。", "district_encode": "440306", "org_cn_introduction": "深圳市景旺电子股份有限公司是一家专业从事印刷电路板及高端电子材料研发、生产和销售的国家高新技术企业，公司产品类型覆盖FR4印制电路板、铝基电路板、柔性电路板、HDI板、刚挠结合板、高端电子材料等。公司深耕印制电路板行业二十八年，专注于印制电路板的生产、研发和销售，已成为印制电路板行业内的重要品牌之一，是中国电子电路行业协会副理事长单位，是行业标准的制定单位之一。", "legal_representative": "刘绍柏", "general_manager": "刘绍柏", "secretary": "黄恬", "established_date": 731606400000, "reg_asset": 852136176.0, "staff_num": 12117, "telephone": "86-755-83892180", "postcode": "518054", "fax": "86-755-83893909", "email": "stock@kinwong.com", "org_website": "www.kinwong.com", "reg_address_cn": "广东省深圳市宝安区西乡街道铁岗水库路166号", "reg_address_en": "", "office_address_cn": "广东省深圳市南山区海德三道天利中央商务广场C座19层", "office_address_en": "", "currency_encode": "019001", "currency": "CNY", "listed_date": 1483632000000, "provincial_name": "广东省", "actual_controller": "黄小芬 (34.49%)，卓军 (34.42%)，刘绍柏 (0.07%)", "classi_name": "民营企业", "pre_name_cn": null, "chairman": "刘绍柏", "executives_nums": 15, "actual_issue_vol": 48000000.0, "issue_price": 23.16, "actual_rc_net_amt": 1051968100.0, "pe_after_issuing": 22.97, "online_success_rate_of_issue": 0.04227287, "affiliate_industry": {"ind_code": "BK0021", "ind_name": "半导体及元件"}}