{"org_id": "02600638", "org_name_cn": "上海新黄浦实业集团股份有限公司", "org_short_name_cn": "新黄浦", "org_name_en": "Shanghai New Huang Pu Industrial Group Co.,Ltd.", "org_short_name_en": "NHPIGCL", "main_operation_business": "房地产开发与销售。", "operating_scope": "　　房地产经营，旧危房改造，室内外建筑装潢，物业管理，房产咨询，机械设备安装（含维修），餐饮业，旅馆业；销售装潢材料、金属材料、木材、建筑材料、五金交电、百货、化工原料（除危险品）、电工器材、汽车配件。【依法须经批准的项目，经相关部门批准后方可开展经营活动】。", "district_encode": "310101", "org_cn_introduction": "上海新黄浦实业集团股份有限公司的主营业务为房地产开发与销售,经营模式以自主开发、销售、出租为主。公司的业务板块分为商业办公地产开发、住宅地产开发和园区建设开发等。目前公司房地产开发的业务范围主要集中在上海、浙江、江苏。公司房地产开发业务的主要产品为高端办公楼、普通商品房、酒店式公寓、科技园区、保障性住宅、长租房、多层洋房和别墅等。", "legal_representative": "赵峥嵘", "general_manager": "赵峥嵘", "secretary": "徐俊", "established_date": 713808000000, "reg_asset": 673396786.0, "staff_num": 749, "telephone": "86-21-63238888", "postcode": "200001", "fax": "86-21-63237777", "email": "stock@600638.com;600638@600638.com", "org_website": "www.600638.com", "reg_address_cn": "上海市黄浦区北京东路668号东楼32层", "reg_address_en": "", "office_address_cn": "上海市黄浦区北京东路668号东楼32层", "office_address_en": "", "currency_encode": "019001", "currency": "CNY", "listed_date": 733075200000, "provincial_name": "上海市", "actual_controller": "北京市人民政府 (5.09%)", "classi_name": "省属国资控股", "pre_name_cn": "上海新黄浦置业股份有限公司", "chairman": "赵峥嵘", "executives_nums": 17, "actual_issue_vol": 6344500.0, "issue_price": 60.8, "actual_rc_net_amt": 482182000.0, "pe_after_issuing": null, "online_success_rate_of_issue": null, "affiliate_industry": {"ind_code": "BK0053", "ind_name": "房地产开发"}}