{"org_id": "03130778", "org_name_cn": "宁波能源集团股份有限公司", "org_short_name_cn": "宁波能源", "org_name_en": "Ningbo Energy Group Co.,Ltd.", "org_short_name_en": "NBEG", "main_operation_business": "热电联产、生物质发电、抽水蓄能和综合能源服务，以及能源类相关金融投资等业务。", "operating_scope": "　　电力电量、热量、灰渣的生产及其咨询服务。（依法须经批准的项目，经相关部门批准后方可开展经营活动）", "district_encode": "330206", "org_cn_introduction": "宁波能源集团股份有限公司主要从事热电联产、生物质发电、抽水蓄能和综合能源服务，以及能源类相关金融投资等业务。公司主要产品是热力与电力,通过煤燃烧产生蒸汽提供给工业用户,同时通过汽轮机发电,直接接入电网。公司十多年来已连续为宁波北仑经济技术开发区和宁波保税区数十家纺织、化工、食品企业提供热力和电力。", "legal_representative": "马奕飞", "general_manager": "诸南虎", "secretary": "沈琦", "established_date": 809107200000, "reg_asset": 1117768211.0, "staff_num": 1135, "telephone": "86-574-86897102", "postcode": "315042", "fax": "86-574-87008281", "email": "nbtp@nbtp.com.cn", "org_website": "www.nbtp.com.cn", "reg_address_cn": "浙江省宁波市北仑区经济技术开发区大港工业城", "reg_address_en": "", "office_address_cn": "浙江省宁波市鄞州区昌乐路187号发展大厦B座6-8F", "office_address_en": "", "currency_encode": "019001", "currency": "CNY", "listed_date": 1089043200000, "provincial_name": "浙江省", "actual_controller": "宁波市国有资产监督管理委员会 (45.84%)", "classi_name": "地市国资控股", "pre_name_cn": "宁波热电股份有限公司", "chairman": "马奕飞", "executives_nums": 16, "actual_issue_vol": 50000000.0, "issue_price": 4.2, "actual_rc_net_amt": 193385000.0, "pe_after_issuing": 17.5, "online_success_rate_of_issue": null, "affiliate_industry": {"ind_code": "BK0045", "ind_name": "电力"}}