{"org_id": "03130034", "org_name_cn": "安阳钢铁股份有限公司", "org_short_name_cn": "安阳钢铁", "org_name_en": "Anyang Iron And Steel Co.,Ltd.", "org_short_name_en": "AYIS", "main_operation_business": "研究开发、生产和经营冶金产品、副产品，钢铁延伸产品、冶金产品的原材料、化工产品等。", "operating_scope": "　　生产和经营冶金产品、副产品、钢铁延伸产品、冶金产品的原材料、化工产品（不含易燃易爆危险品）；冶金技术开发、协作、咨询，实业投资（国家专项规定的除外）。经营本企业自产产品的出口业务和本企业所需的机械设备、零配件、原辅材料的进口业务（国家限定公司经营或禁止进出口的商品和技术除外）。医用氧的生产（凭许可证经营）。苯、萘、蒽油乳剂、煤焦酚、煤焦沥青、煤焦油、硫磺、氧（压缩的）、氧（液化的）、氮（压缩的）、氮（液化的）、氩（压缩的）、氩（液化的）、硫酸的经营（无仓储，凭许可证经营）。（以下限分支机构经营）冶金成套设备的制作，各类机电设备零部件，轧辊、金属结构件的加工、安装、修理和铸件、锻件、钢木模具的制作及零部件表面修复；大型设备、构件吊装运输。（依法须经批准的项目，经相关部门批准后方可开展经营活动）", "district_encode": "410505", "org_cn_introduction": "安阳钢铁股份有限公司的主营业务为研究开发、生产和经营冶金产品、副产品，钢铁延伸产品、冶金产品的原材料、化工产品等。公司的主要产品为型材、建材、板材。", "legal_representative": "李利剑", "general_manager": "于银俊", "secretary": "郭成许", "established_date": 753292800000, "reg_asset": 2872421386.0, "staff_num": 15347, "telephone": "86-372-3120175", "postcode": "455004", "fax": "86-372-3120181", "email": "aygtdb312@126.com;aygtzq@126.com", "org_website": "www.aysteel.com.cn", "reg_address_cn": "河南省安阳市殷都区梅元庄", "reg_address_en": "", "office_address_cn": "河南省安阳市殷都区梅元庄", "office_address_en": "", "currency_encode": "019001", "currency": "CNY", "listed_date": 998236800000, "provincial_name": "河南省", "actual_controller": "河南省人民政府国有资产监督管理委员会 (66.78%)", "classi_name": "省属国资控股", "pre_name_cn": null, "chairman": "李利剑", "executives_nums": 21, "actual_issue_vol": 275000000.0, "issue_price": 6.8, "actual_rc_net_amt": 1829250000.0, "pe_after_issuing": 19.59, "online_success_rate_of_issue": 5.032, "affiliate_industry": {"ind_code": "BK0012", "ind_name": "钢铁"}}