{"org_id": "T000053334", "org_name_cn": "桂林福达股份有限公司", "org_short_name_cn": "福达股份", "org_name_en": "Guilin Fuda Co.,Ltd.", "org_short_name_en": "", "main_operation_business": "主要从事汽车、工程机械、农机、船舶等动力机械发动机曲轴、汽车离合器、螺旋锥齿轮、精密锻件和高强度螺栓的研发、生产与销售。", "operating_scope": "　　从事汽车零部件和部件系统的研发、生产与销售；技术服务；商务服务。（依法须经批准的项目，经相关部门批准后方可开展经营活动）。", "district_encode": "450312", "org_cn_introduction": "桂林福达股份有限公司主要从事汽车、工程机械、农机、船舶等动力机械发动机曲轴、汽车离合器、螺旋锥齿轮、精密锻件和高强度螺栓的研发、生产与销售。主要产品为曲轴、离合器、齿轮、精密锻件、高强度螺栓等。", "legal_representative": "黎福超", "general_manager": "黎锋", "secretary": "张海涛", "established_date": 977932800000, "reg_asset": 646208651.0, "staff_num": 2626, "telephone": "86-773-3681001", "postcode": "541199", "fax": "86-773-3681002", "email": "foto@glfoto.cn", "org_website": "www.glfoto.cn", "reg_address_cn": "广西壮族自治区桂林市临桂区西城经济开发区秧塘工业园秧十八路东侧", "reg_address_en": "", "office_address_cn": "广西壮族自治区桂林市临桂区西城经济开发区秧塘工业园秧十八路东侧", "office_address_en": "", "currency_encode": "019001", "currency": "CNY", "listed_date": 1417017600000, "provincial_name": "广西壮族自治区", "actual_controller": "黎福超 (65.67%)", "classi_name": "民营企业", "pre_name_cn": null, "chairman": "黎福超", "executives_nums": 14, "actual_issue_vol": 43500000.0, "issue_price": 5.8, "actual_rc_net_amt": 214849300.0, "pe_after_issuing": 20.0, "online_success_rate_of_issue": 0.29854737, "affiliate_industry": {"ind_code": "BK0026", "ind_name": "汽车零部件"}}