{"org_id": "03134302", "org_name_cn": "北方联合出版传媒(集团)股份有限公司", "org_short_name_cn": "出版传媒", "org_name_en": "North Ernunited Publishing&Media (Group) Company Limited", "org_short_name_en": "NUPMG", "main_operation_business": "教材教辅、一般图书等出版物的出版、发行、印刷以及印刷物资供销等业务。", "operating_scope": "　　图书、报刊、音像、电子出版物编辑出版，出版物总批发、批发与分销、零售，印刷、复制，出版、发行、印刷物资购销，版权贸易和对外出版、发行、印刷贸易，互联网出版、发行，广告、会展、文化服务，境内外投资、资产管理与经营业务，计算机信息系统集成及软件开发、技术转让、技术服务、技术咨询，计算机网络及配套设备销售，电讯器材销售，安全防范工程设计、安装、技术服务，网络产品研发、销售，电子产品、数控机床、仪器仪表、教学仪器设备销售，增值电信业务经营，教育辅助服务。（以上项目涉及行政许可的，由分支机构凭许可证经营）", "district_encode": "210102", "org_cn_introduction": "北方联合出版传媒(集团)股份有限公司主营业务为教材教辅、一般图书等出版物的出版、发行、印刷以及印刷物资供销等业务。主要产品有图书出版业务、图书发行业务、印刷业务、物资供应业务。", "legal_representative": "杨建军", "general_manager": "陈闯", "secretary": "费宏伟", "established_date": 1156780800000, "reg_asset": 550914700.0, "staff_num": 2334, "telephone": "86-24-23285500", "postcode": "110003", "fax": "86-24-23284232", "email": "601999@nupmg.com", "org_website": "www.nupmg.com", "reg_address_cn": "辽宁省沈阳市和平区十一纬路29号", "reg_address_en": "", "office_address_cn": "辽宁省沈阳市和平区十一纬路29号", "office_address_en": "", "currency_encode": "019001", "currency": "CNY", "listed_date": 1198166400000, "provincial_name": "辽宁省", "actual_controller": "辽宁省人民政府国有资产监督管理委员会 (67.52%)", "classi_name": "省属国资控股", "pre_name_cn": "辽宁出版传媒股份有限公司", "chairman": "杨建军", "executives_nums": 12, "actual_issue_vol": 140000000.0, "issue_price": 4.64, "actual_rc_net_amt": 617905456.0, "pe_after_issuing": 29.98, "online_success_rate_of_issue": 0.29074122, "affiliate_industry": {"ind_code": "BK0064", "ind_name": "传媒"}}