{"org_id": "03130088", "org_name_cn": "中文天地出版传媒集团股份有限公司", "org_short_name_cn": "中文传媒", "org_name_en": "Chinese Universe Publishing And Media Group Co.,Ltd.", "org_short_name_en": "CHINESE MEDIA", "main_operation_business": "书刊和音像电子出版物编辑出版、印刷发行、物资供应等传统出版业务;国内外贸易和供应链业务、现代物流和物联网技术应用等产业链延伸业务;新媒体、在线教育、互联网游戏、数字出版、影视剧生产、艺术品经营、文化综合体和投融资等新业态业务。", "operating_scope": "　　国内版图书、电子、期刊批发兼零售(许可证有效期至2022年06月30日)；文化艺术品经营；各类广告的制作、发布、代理；会议及展览服务；国内外贸易；资产管理与投资；房地产开发与销售；以下项目限分支机构经营：图书、报刊、音像、电子出版物的出版；影视制作与发行；互联网文化产品的制作、经营及其服务；出版物零售；文化经纪；仓储、物流与配送服务。（依法须经批准的项目，经相关部门审批后方可开展经营活动）", "district_encode": "361104", "org_cn_introduction": "中文天地出版传媒集团股份有限公司主营涵盖书刊和音像电子出版物编辑出版、印刷发行、物资供应等传统出版业务;国内外贸易和供应链业务、现代物流和物联网技术应用等产业链延伸业务;新媒体、在线教育、互联网游戏、数字出版、影视剧生产、艺术品经营、文化综合体和投融资等新业态业务。主要产品有图书、教材教辅、音像及数码产品、印刷包装、物流、物资贸易、新业态等。公司屡获“中国企业信用500强”“中国服务业企业信用100强”“中国上市公司信用100强”等殊荣，并荣获“中国主板上市公司价值百强”“高质量发展先锋”等荣誉。", "legal_representative": "吴信根", "general_manager": "吴涤", "secretary": "毛剑波", "established_date": 912355200000, "reg_asset": 1355063719.0, "staff_num": 6527, "telephone": "86-791-85896008", "postcode": "330038", "fax": "86-791-85896008", "email": "zwcm600373@126.com", "org_website": "www.600373.com.cn", "reg_address_cn": "江西省上饶市广信区上饶经济技术开发区兴园大道32号双创科技城10号楼", "reg_address_en": "", "office_address_cn": "江西省南昌市东湖区红谷滩新区学府大道299号", "office_address_en": "", "currency_encode": "019001", "currency": "CNY", "listed_date": 1015171200000, "provincial_name": "江西省", "actual_controller": "江西省人民政府 (55.76%)", "classi_name": "省属国资控股", "pre_name_cn": "中文天地出版传媒股份有限公司", "chairman": "吴信根", "executives_nums": 23, "actual_issue_vol": 45000000.0, "issue_price": 2.68, "actual_rc_net_amt": 112602000.0, "pe_after_issuing": 20.0, "online_success_rate_of_issue": 0.0562, "affiliate_industry": {"ind_code": "BK0064", "ind_name": "传媒"}}