{"org_id": "T000252308", "org_name_cn": "安徽壹石通材料科技股份有限公司", "org_short_name_cn": "壹石通", "org_name_en": "Anhui Estone Materials Technology Co., Ltd.", "org_short_name_en": "", "main_operation_business": "先进无机非金属复合材料的研发、生产和销售。", "operating_scope": "　　二氧化硅、氧化铝、氢氧化铝、勃姆石、硼酸锌、氧化锆、锂霞石、硅碳复合材料等无机阻燃及无机非金属粉体材料；铝粉、铁粉等金属粉体材料；聚合物复合材料、金属基复合材料、陶瓷基复合材料、锂电池正极材料、锂电池负极材料、碳基导电材料及相关材料的研发、生产、销售；自营和代理上述商品和技术的进出口业务（国家限定公司经营或禁止出口的商品和技术除外）。（依法须经批准的项目，经相关部门批准后方可开展经营活动）", "district_encode": "340321", "org_cn_introduction": "安徽壹石通材料科技股份有限公司的主营业务为先进无机非金属复合材料的研发、生产和销售，主要产品包括锂电池主动安全材料、电子通信功能材料和低烟无卤阻燃材料等三大类。无机非金属材料具备绝缘性好、耐热性强、化学性能稳定等特点，被广泛应用于新能源汽车、消费电子、芯片、覆铜板以及防火安全等领域。根据高工产业研究院统计，2018及2019年，公司的锂电池用勃姆石出货量位列全国第一、全球第二。公司的电子通信功能填充材料已通过向生益科技提供产品进入了华为5G产品供应链。以公司低烟无卤阻燃材料作为阻燃剂的电线电缆经国家电线电缆质量监督中心检测，阻燃性能达到国家消防标准化技术委员会认定的阻燃指标下的最高等级。", "legal_representative": "蒋学鑫", "general_manager": "蒋学鑫", "secretary": "邵森", "established_date": 1136476800000, "reg_asset": 182164340.0, "staff_num": 325, "telephone": "86-552-8220958", "postcode": "233400", "fax": "86-552-8599966", "email": "ir@estonegroup.com", "org_website": "www.estonegroup.com", "reg_address_cn": "安徽省蚌埠市怀远县经济开发区金河路10号", "reg_address_en": "", "office_address_cn": "安徽省蚌埠市怀远县经济开发区金河路10号", "office_address_en": "", "currency_encode": "019001", "currency": "CNY", "listed_date": 1629129600000, "provincial_name": "安徽省", "actual_controller": "蒋学鑫 (27.26%)，王亚娟 (4.78%)", "classi_name": "民营企业", "pre_name_cn": null, "chairman": "蒋学鑫", "executives_nums": 15, "actual_issue_vol": 45541085.0, "issue_price": 15.49, "actual_rc_net_amt": 629512300.0, "pe_after_issuing": 91.93, "online_success_rate_of_issue": 0.02612625, "affiliate_industry": {"ind_code": "BK0014", "ind_name": "新材料"}}