{"org_id": "T004807885", "org_name_cn": "恒玄科技(上海)股份有限公司", "org_short_name_cn": "恒玄科技", "org_name_en": "Bestechnic (Shanghai) Co.,Ltd.", "org_short_name_en": "BES", "main_operation_business": "智能音频SoC芯片设计、研发及销售。", "operating_scope": "　　从事电子科技、通信科技、网络科技、计算机科技领域内的技术开发、技术咨询、技术服务、技术转让,上述技术及电子产品及设备、计算机软件(音像制品及电子出版物除外)及辅助设备的批发、进出口、佣金代理(拍卖除外)及其相关配套服务,半导体集成电路芯片及计算机软、硬件的设计、研发、销售,计算机信息系统集成。【依法须经批准的项目,经相关部门批准后方可开展经营活动】", "district_encode": "310115", "org_cn_introduction": "恒玄科技(上海)股份有限公司主营业务为智能音频SoC芯片的研发、设计与销售，公司产品主要分为普通蓝牙音频芯片、智能蓝牙音频芯片和Type-C音频芯片三类。公司已成为全球智能音频SoC芯片领域的领先供应商，产品及技术能力获得客户广泛认可，是大陆地区少数可与高通、联发科等国际巨头竞争的芯片设计公司。公司已连续两年荣获EETimes评选的中国IC设计成就奖，同时是中国电子音响行业协会理事会常务理事单位。", "legal_representative": "Liang Zhang", "general_manager": "Liang Zhang", "secretary": "李广平", "established_date": 1433692800000, "reg_asset": 120000000.0, "staff_num": 243, "telephone": "86-21-6877-1788-6666", "postcode": "201203", "fax": "86-21-6877-1788-1111", "email": "ir@bestechnic.com", "org_website": "www.bestechnic.com", "reg_address_cn": "上海市浦东新区中国(上海)自由贸易试验区临港新片区环湖西二路800号904室", "reg_address_en": "", "office_address_cn": "上海市浦东新区金科路2889弄长泰广场B座201室", "office_address_en": "", "currency_encode": "019001", "currency": "CNY", "listed_date": 1608048000000, "provincial_name": "上海市", "actual_controller": "汤晓冬 (11.30%)，赵国光 (10.26%)，Liang Zhang (4.12%)", "classi_name": "民营企业", "pre_name_cn": "恒玄科技(上海)有限公司", "chairman": "Liang Zhang", "executives_nums": 13, "actual_issue_vol": 30000000.0, "issue_price": 162.07, "actual_rc_net_amt": 4758781200.0, "pe_after_issuing": 355.03, "online_success_rate_of_issue": 0.02925325, "affiliate_industry": {"ind_code": "BK0021", "ind_name": "半导体及元件"}}