{"org_id": "T000678216", "org_name_cn": "无锡航亚科技股份有限公司", "org_short_name_cn": "航亚科技", "org_name_en": "Wuxi Hyatech Co.,Ltd.", "org_short_name_en": "HYATECH", "main_operation_business": "专注于航空发动机关键零部件及医疗骨科植入锻件的研发、生产及销售。", "operating_scope": "　　航空发动机零部件、燃气轮机零部件、精密机械零部件、医疗骨科植入锻件的研发、生产、销售。产品特征特性检测服务。自营各类商品及技术的进出口业务（国家限定公司经营或禁止进出口的商品和技术除外）。（依法须经批准的项目，经相关部门批准后方可开展经营活动）", "district_encode": "320214", "org_cn_introduction": "无锡航亚科技股份有限公司是一家专业的航空发动机及医疗骨科领域的高性能零部件制造商，专注于航空发动机关键零部件及医疗骨科植入锻件的研发、生产及销售，主要产品包括航空涡扇发动机压气机叶片、转动件及结构件(整体叶盘、整流器、机匣、涡轮盘及压气机盘等盘环件、转子组件等)、医疗骨科植入锻件等高性能零部件。", "legal_representative": "严奇", "general_manager": "朱宏大", "secretary": "卫喆", "established_date": 1359475200000, "reg_asset": 258382608.0, "staff_num": 400, "telephone": "86-510-81893698", "postcode": "214142", "fax": "86-510-81893692", "email": "irm@hyatech.cn", "org_website": "www.hyatech.cn", "reg_address_cn": "江苏省无锡市新吴区新东安路35号", "reg_address_en": "", "office_address_cn": "江苏省无锡市新吴区新东安路35号", "office_address_en": "", "currency_encode": "019001", "currency": "CNY", "listed_date": 1608048000000, "provincial_name": "江苏省", "actual_controller": "严奇 (14.44%)", "classi_name": "民营企业", "pre_name_cn": null, "chairman": "严奇", "executives_nums": 19, "actual_issue_vol": 64600000.0, "issue_price": 8.17, "actual_rc_net_amt": 474312146.99999994, "pe_after_issuing": 53.35, "online_success_rate_of_issue": 0.03150092, "affiliate_industry": {"ind_code": "BK0066", "ind_name": "国防军工"}}