{"org_id": "01000676", "org_name_cn": "智度科技股份有限公司", "org_short_name_cn": "智度股份", "org_name_en": "Genimous Technology Co.,Ltd.", "org_short_name_en": "Genimous Technology", "main_operation_business": "互联网媒体业务、数字营销业务及其他业务。", "operating_scope": "　　从事网络科技、计算机科技领域内的技术开发、技术咨询、技术服务、技术转让；基础软件、应用软件服务（不含医用软件）及自助研发产品销售；网络游戏开发、运营与维护；数码产品、机电产品、日用百货、计算机、软件及辅助设备的批发与零售；互联网信息服务；电信业务（第二类增值电信业务中的信息服务业务，仅限互联网信息服务）；设计、制作、代理、发布广告；互联网文化活动；文艺创作及表演；会务服务；企业形象策划；市场营销策划；商务咨询；自营和代理技术的进出口业务（国家限定公司经营或禁止进出口的商品及技术除外）；投资与资产管理；投资咨询；经济贸易咨询。（依法须经批准的项目，经相关部门批准后方可开展经营活动）。", "district_encode": "440114", "org_cn_introduction": "智度科技股份有限公司主营业务为互联网媒体业务、数字营销业务及其他业务。公司主要产品或服务有移动互联网广告、网络游戏、搜索引擎广告代理、精准广告、供应商销售竞价平台服务、社会化营销、娱乐影视跨界营销、互联网软件应用分发。", "legal_representative": "陆宏达", "general_manager": "陈志峰", "secretary": "孙静", "established_date": 850665600000, "reg_asset": 1276506972.0, "staff_num": 895, "telephone": "86-10-66237897", "postcode": "100031", "fax": "86-10-66237715", "email": "zhidugufen@genimous.com", "org_website": "www.genimous.com", "reg_address_cn": "广东省广州市花都区新雅街凤凰南路56之三401室(部位之8)", "reg_address_en": "", "office_address_cn": "北京市西城区西绒线胡同51号北门", "office_address_en": "", "currency_encode": "019001", "currency": "CNY", "listed_date": 851356800000, "provincial_name": "广东省", "actual_controller": "吴红心 (4.36%)", "classi_name": "民营企业", "pre_name_cn": "智度投资股份有限公司", "chairman": "陆宏达", "executives_nums": 11, "actual_issue_vol": 12500000.0, "issue_price": 5.2, "actual_rc_net_amt": 60000000.0, "pe_after_issuing": 17.5, "online_success_rate_of_issue": 1.351, "affiliate_industry": {"ind_code": "BK0064", "ind_name": "传媒"}}