{"org_id": "T000377382", "org_name_cn": "青岛英派斯健康科技股份有限公司", "org_short_name_cn": "英派斯", "org_name_en": "Impulse(Qingdao)Health Tech Co.,Ltd.", "org_short_name_en": "IMPULSE", "main_operation_business": "专注于全品类、多系列健身器材开发制造及销售、品牌化运营。", "operating_scope": "　　生产、销售钢管制品、钢塑制品及配件、健身器材及配件、气膜场馆设施及配件、钢结构场馆设施及配件、笼式体育运动场地设施及配件、拆装式游泳池设施及配件、水上体育器材及配件、办公家具及配件、食品设备及配件、太阳能产品及配件、电子设备及附件、体质监测设备、医疗器械、康复训练器材及设备、运动地板地胶、文化体育用品（各类球、球拍、服装鞋帽等）、儿童滑梯、游乐设施；体育公园规划设计、体育场地设施施工及场地改造、市政公用工程、装饰装潢工程、建筑总承包；体育健身器材的维修、安装及售后服务；设计、制作、代理、发布国内广告；技术服务、软件服务、软件开发、体能训练技术推广、健身指导、健身咨询、信息咨询、教育咨询、体能训练技术咨询；体育竞赛组织，体育赛事策划。（依法须经批准的项目，经相关部门批准后方可开展经营活动）", "district_encode": "370215", "org_cn_introduction": "青岛英派斯健康科技股份有限公司主营业务为专注于全品类、多系列健身器材开发制造及销售、品牌化运营。主要产品为R系列、P系列、EXO-FORM系列、IE系列、IT系列、IF系列、ENCORE系列、Zone系列、有氧跑步机系列、家用健身车系列、风帆系列、灵动系列、非凡系列、场地设施。\r\n　　截至2019年6月30日，公司拥有各项专利187项，其中发明专利20项。截至报告期末，公司荣获了“2019台北国际体育用品展创新奖入选奖”（中国大陆唯一入选的企业）、“国家知识产权示范企业”、“中国健身器材行业最佳创新企业”、“中国工业设计十佳创新型企业”、“中国轻工业优秀设计奖金奖”、“山东省省长杯工业设计大奖赛铜奖”、山东省第二届“省长杯”工业设计大赛优秀奖等荣誉，公司产品技术开发部门被评为“国家认定企业技术中心”、“山东省省级工业设计中心”。", "legal_representative": "丁利荣", "general_manager": "丁利荣", "secretary": "张瑞", "established_date": 1087920000000, "reg_asset": 120000000.0, "staff_num": 1563, "telephone": "86-532-85793159", "postcode": "266061", "fax": "86-532-85793159", "email": "information@impulsefitness.com", "org_website": "www.impulsefitness.com", "reg_address_cn": "山东省青岛市即墨区华山二路369号", "reg_address_en": "", "office_address_cn": "山东省青岛市崂山区秦岭路18号国展财富中心3号楼7层", "office_address_en": "", "currency_encode": "019001", "currency": "CNY", "listed_date": 1505404800000, "provincial_name": "山东省", "actual_controller": "丁利荣 (30.50%)", "classi_name": "民营企业", "pre_name_cn": "青岛英派斯健康科技有限公司", "chairman": "丁利荣", "executives_nums": 14, "actual_issue_vol": 30000000.0, "issue_price": 16.05, "actual_rc_net_amt": 433205400.0, "pe_after_issuing": 22.99, "online_success_rate_of_issue": 0.02360191, "affiliate_industry": {"ind_code": "BK0039", "ind_name": "家用轻工"}}