{"org_id": "01000605", "org_name_cn": "渤海水业股份有限公司", "org_short_name_cn": "渤海股份", "org_name_en": "Bohai Water Industry Co.,Ltd.", "org_short_name_en": "BHWI", "main_operation_business": "原水和自来水开发供应、管道输水运输、供水设施管理、维护和保养、水务基础设施投资建设及运营管理。", "operating_scope": "　　工程设计；施工总承包、专业承包、劳务分包；城乡公用基础设施、水土环境治理及环保项目、供水、污水治理及再生水利用的投资；投资咨询；投资管理；技术开发；技术咨询；技术服务；技术推广；企业管理。（领取本执照后，应到市规划委、市住建委取得行政许可；企业依法自主选择经营项目，开展经营活动；依法须经批准的项目，经相关部门批准后依批准的内容开展经营活动；不得从事本市产业政策禁止和限制类项目的经营活动。）", "district_encode": "110113", "org_cn_introduction": "渤海水业股份有限公司主营业务为原水和自来水开发供应、管道输水运输、供水设施管理、维护和保养、水务基础设施投资建设及运营管理。公司获得2013水务旗舰企业、2013年度中国水业市政供水领域多水源延伸的区域水务年度标杆企业等多项荣誉。\r\n　　公司于2017年7月完成重大资产重组，重组前公司名称为四环药业股份有限公司，主营业务为生物医药、中西药的研究开发；小容量注射剂、冻干粉针剂的生产销售；\"欧力康牌玄驹口服液\"保健食品的委托加工及销售;医疗器械经营等。", "legal_representative": "刘瑞深", "general_manager": "王立林", "secretary": "李新霞", "established_date": 842284800000, "reg_asset": 352658600.0, "staff_num": 1692, "telephone": "86-10-89586598", "postcode": "101100", "fax": "86-10-89586920", "email": "dongmi@bohai-water.com", "org_website": "www.bohai-water.com", "reg_address_cn": "北京市顺义区中关村科技园顺义园临空二路1号", "reg_address_en": "", "office_address_cn": "北京市通州区潞苑南大街290号", "office_address_en": "", "currency_encode": "019001", "currency": "CNY", "listed_date": 842544000000, "provincial_name": "北京市", "actual_controller": "天津市人民政府国有资产监督管理委员会 (38.59%)", "classi_name": "省属国资控股", "pre_name_cn": "四环药业股份有限公司", "chairman": "刘瑞深", "executives_nums": 20, "actual_issue_vol": 12500000.0, "issue_price": 4.0, "actual_rc_net_amt": 47500000.0, "pe_after_issuing": 14.81, "online_success_rate_of_issue": 3.6119, "affiliate_industry": {"ind_code": "BK0046", "ind_name": "燃气水务"}}