{"org_id": "T000026770", "org_name_cn": "浙江亚厦装饰股份有限公司", "org_short_name_cn": "亚厦股份", "org_name_en": "Zhejiang Yasha Decoration Co.,Ltd", "org_short_name_en": "YASHA", "main_operation_business": "建筑装饰装修工程、建筑幕墙工程、智能化系统集成。", "operating_scope": "　　建筑装饰装修工程、建筑幕墙工程、钢结构工程、消防工程、水电工程、园林绿化工程、建筑智能化工程的设计、施工，石材加工，建筑幕墙、铝制品、金属门窗、建筑装饰材料、五金制品、家俱、木制品的生产、销售，广告设计、制作，经营进出口业务；承包境外建筑装修装饰、建筑幕墙工程和境内国际招标工程，承包上述工程的勘测、咨询、设计和监理项目，承包上述境外工程所需的设备、材料、对外派遣实施上述境外工程所需的劳务人员。", "district_encode": "330604", "org_cn_introduction": "浙江亚厦装饰股份有限公司主营业务为建筑装饰装修工程、建筑幕墙工程、智能化系统集成。公司是中国建筑装饰行业领跑者。主要产品有建筑装饰工程、幕墙装饰工程、智能化系统集成、装饰制品销售、设计合同。公司已连续14年蝉联中国建筑装饰百强企业第二名,亚厦幕墙连续2年获得中国建筑幕墙行业百强企业第二名,综合实力位居行业前列。公司是行业首家“国家高新技术企业”、“全国重合同守信用单位”、“全国建筑装饰行业首批AAA信用等级企业”、“亚太最佳上市公司50强”,拥有建筑装饰行业唯一一家国家住宅产业化基地、国家装配式建筑产业基地和CNAS实验室。", "legal_representative": "张小明", "general_manager": "张小明", "secretary": "戴轶钧", "established_date": 805046400000, "reg_asset": 1339996498.0000002, "staff_num": 7105, "telephone": "86-571-28208786", "postcode": "310008", "fax": "86-571-28208785", "email": "yasha_002375@163.com", "org_website": "www.chinayasha.com", "reg_address_cn": "浙江省绍兴市上虞区章镇工业新区", "reg_address_en": "", "office_address_cn": "浙江省杭州市西湖区沙秀路99号亚厦中心A座", "office_address_en": "", "currency_encode": "019001", "currency": "CNY", "listed_date": 1269273600000, "provincial_name": "浙江省", "actual_controller": "丁欣欣 (31.32%)，张杏娟 (20.80%)", "classi_name": "民营企业", "pre_name_cn": null, "chairman": "丁泽成", "executives_nums": 14, "actual_issue_vol": 53000000.0, "issue_price": 31.86, "actual_rc_net_amt": 1620631200.0, "pe_after_issuing": 50.57, "online_success_rate_of_issue": 0.58662383, "affiliate_industry": {"ind_code": "BK0016", "ind_name": "建筑装饰"}}