{"org_id": "01000022", "org_name_cn": "招商局港口集团股份有限公司", "org_short_name_cn": "招商港口", "org_name_en": "China Merchants Port Group Co., Ltd.", "org_short_name_en": "CMPort", "main_operation_business": "从事集装箱和散杂货的港口装卸、仓储、运输及其它配套服务", "operating_scope": "　　港口码头建设、管理和经营;进出口各类货物保税仓储业务;港口配套园区的开发、建设和运营;国际、国内货物的装卸、中转、仓储、运输,货物加工处理;集装箱拆拼箱、清洗、修理、制造和租赁;国际货运代理;租车租船业务;为船舶提供燃物料、生活品供应等船舶港口服务;船舶拖带(不得使用外国籍船舶经营);港口设施、设备和港口机械的租赁、维修服务;自营和代理各类货物和技术的进出口,但国家限制或禁止进出口的货物和技术除外;港口物流及港口信息技术咨询服务;现代物流信息系统的技术开发、技术服务;供应链管理及相关配套服务;物流方案设计;工程项目管理;港务工程技术的开发、研究、咨询服务。(依法须经批准的项目,经相关部门批准后依批准的内容开展经营活动)。", "district_encode": "440305", "org_cn_introduction": "招商局港口集团股份有限公司主要从事集装箱和散杂货的港口装卸、仓储、运输及其它配套服务,主要经营深圳西部港区24个集装箱泊位和15个散杂货泊位,汕头港9个集装箱泊位、2个散杂货泊位,10个件杂货泊位,1个煤炭专用泊位,湛江港2个集装箱泊位、33个散货泊位,顺德港4个多功能泊位,漳州港2个集装箱泊位、6个散货泊位,斯里兰卡CICT4个集装箱泊位、HIPG4个多功能泊位、2个油品泊位和4个集装箱泊位,多哥LCT3个集装箱泊位,巴西TCP4个集装箱泊位。公司是中国最大，全球领先的港口开发、投资和运营商。", "legal_representative": "王秀峰", "general_manager": "", "secretary": "李玉彬", "established_date": 648313200000, "reg_asset": 1922365124.0, "staff_num": 15619, "telephone": "86-755-26828888", "postcode": "518067", "fax": "86-755-26886666", "email": "cmpir@cmhk.com", "org_website": "www.cmp1872.com", "reg_address_cn": "广东省深圳市南山区招商街道工业三路一号招商局港口大厦23-25楼", "reg_address_en": "", "office_address_cn": "广东省深圳市南山区招商街道工业三路一号招商局港口大厦23-25楼", "office_address_en": "", "currency_encode": "019001", "currency": "CNY", "listed_date": 736531200000, "provincial_name": "广东省", "actual_controller": "国务院国有资产监督管理委员会 (69.35%)", "classi_name": "央企国资控股", "pre_name_cn": "深圳赤湾港航股份有限公司", "chairman": "邓仁杰", "executives_nums": 18, "actual_issue_vol": 46000000.0, "issue_price": 3.1, "actual_rc_net_amt": 138000000.0, "pe_after_issuing": null, "online_success_rate_of_issue": null, "affiliate_industry": {"ind_code": "BK0048", "ind_name": "港口航运"}}