{"org_id": "T000045455", "org_name_cn": "浙江世纪华通集团股份有限公司", "org_short_name_cn": "世纪华通", "org_name_en": "Zhejiang Century Huatong Group Co.,Ltd", "org_short_name_en": "CENTURY HUATONG", "main_operation_business": "互联网游戏、汽车零部件制造与互联网数据中心。", "operating_scope": "　　汽车配件、摩托车配件、精密金属模具制造、加工、销售；金属冲压件、注塑件设计、生产、销售；塑料粒子、金属制品的批发；计算机软硬件的技术开发、技术咨询、技术服务及销售；纺织品、服装、橡胶制品、塑料制品、金属制品、通信设备、计算机及电子设备、机电设备的批发，佣金代理（拍卖除外）及其进出口业务。上述涉及许可证管理的凭证经营。（依法须经批准的项目，经相关部门批准后方可开展经营活动）", "district_encode": "330604", "org_cn_introduction": "浙江世纪华通集团股份有限公司主要分为互联网游戏与汽车零部件制造，自2020年第三季度始公司增加了IDC数据中心业务板块。主要产品和服务为铜杆加工件、汽车零部件、游戏运营收入、游戏授权收入、游戏开发收入、游戏软件销售等。互联网方面，公司旗下拥有丰富的自主IP储备，包括但不限于《热血传奇》、《龙之谷》、《传奇世界》、《彩虹岛》、《英雄年代》、《风云》、《神无月》、《光明勇士》、《遗忘者之旅》等，其产品的生命周期长、用户粘性高，可持续稳定为公司贡献收入。汽车零部件方面，公司检测中心拥有自德国和美国进口的全套塑料理化性能试验设备、测量设备和产品性能试验设备，并于2007年12月通过CNAS国家认可，目前认可范围包括2大类，30个参数，110个标准。", "legal_representative": "谢斐", "general_manager": "谢斐", "secretary": "郦冰洁", "established_date": 1130688000000, "reg_asset": 7452556968.0, "staff_num": 7250, "telephone": "86-575-82148871", "postcode": "312300", "fax": "86-575-82208079", "email": "bingjie_li@sjhuatong.com", "org_website": "www.sjhuatong.com", "reg_address_cn": "浙江省绍兴市上虞区曹娥街道人民越爱路66号5幢", "reg_address_en": "", "office_address_cn": "浙江省绍兴市上虞区曹娥街道人民越爱路66号", "office_address_en": "", "currency_encode": "019001", "currency": "CNY", "listed_date": 1311782400000, "provincial_name": "浙江省", "actual_controller": "王苗通 (17.40%)，王一锋 (0.00%)", "classi_name": "民营企业", "pre_name_cn": "浙江世纪华通车业股份有限公司", "chairman": "王佶", "executives_nums": 17, "actual_issue_vol": 45000000.0, "issue_price": 23.0, "actual_rc_net_amt": 991765000.0, "pe_after_issuing": 25.61, "online_success_rate_of_issue": 0.80900104, "affiliate_industry": {"ind_code": "BK0064", "ind_name": "传媒"}}