{"org_id": "01000761", "org_name_cn": "本钢板材股份有限公司", "org_short_name_cn": "本钢板材", "org_name_en": "Bengang Steel Plates Co.,Ltd.", "org_short_name_en": "BSP", "main_operation_business": "有钢铁冶炼、压延加工、发电、煤化工、特钢型材、铁路、进出口贸易、科研、产品销售等。", "operating_scope": "　　废旧金属（含有色金属）加工、购销，危险化学品生产（有效期至2016年9月11日），煤炭批发经营，炼铁炉料加工，废旧物资购销。钢铁冶炼、压延加工、产品销售，特钢型材、金属加工，货物及技术进出口（国家禁止的品种除外，限制的品种办理许可证后方可经营），计器仪表、机电设备、钢材销售，工业新产品、新工艺、新技术研究，高炉瓦斯灰及废油回收（危险品除外），化肥销售。（依法须经批准的项目，经相关部门批准后方可开展经营活动。）", "district_encode": "210502", "org_cn_introduction": "本钢板材股份有限公司的主营业务是钢铁冶炼、压延加工、发电、煤化工、特钢型材、铁路、进出口贸易、科研、产品销售等。公司的主要产品是汽车表面板、家电板、石油管线钢、集装箱板、船板。", "legal_representative": "高烈", "general_manager": "林东", "secretary": "高德胜", "established_date": 867340800000, "reg_asset": 3885130224.0, "staff_num": 16745, "telephone": "86-24-47827003;86-24-47828980", "postcode": "117000", "fax": "86-24-47827004", "email": "bgbcdm@163.com;bgbcclw@126.com", "org_website": "", "reg_address_cn": "辽宁省本溪市平山区人民路16号", "reg_address_en": "", "office_address_cn": "辽宁省本溪市平山区人民路16号", "office_address_en": "", "currency_encode": "019001", "currency": "CNY", "listed_date": 884793600000, "provincial_name": "辽宁省", "actual_controller": "辽宁省人民政府国有资产监督管理委员会 (57.53%)", "classi_name": "省属国资控股", "pre_name_cn": null, "chairman": "高烈", "executives_nums": 16, "actual_issue_vol": 120000000.0, "issue_price": 5.4, "actual_rc_net_amt": 628800000.0, "pe_after_issuing": 10.0, "online_success_rate_of_issue": 1.0434, "affiliate_industry": {"ind_code": "BK0012", "ind_name": "钢铁"}}