{"org_id": "03132300", "org_name_cn": "山河智能装备股份有限公司", "org_short_name_cn": "山河智能", "org_name_en": "Sunward Intelligent Equipment Co.,Ltd.", "org_short_name_en": "SUNWARD", "main_operation_business": "锚定工程机械、航空装备与服务、特种装备三大业务领域，为全球客户提供整体解决方案。", "operating_scope": "　　研究、设计、生产销售建设机械、工程机械、农业机械、林业机械、矿山机械、起重机械、厂内机动车辆和其他高技术机电一体化产品及其与主机配套的动力、液压、电控系统产品和配件；提供机械设备的租赁、售后服务及相关技术咨询服务；经营商品和技术的进出口业务（国家法律法规禁止和限制的除外）。", "district_encode": "430121", "org_cn_introduction": "山河智能装备股份有限公司锚定工程机械、航空装备与服务、特种装备三大业务领域，不断推出具有世界影响力的产品，为全球客户提供整体解决方案。公司现为国内地下工程装备龙头企业之一，位居全球工程机械制造企业50强、全球挖掘机企业20强、全球支线飞机租赁企业3强。公司自主研制的“山河阿若拉SA60L轻型运动飞机”是我国首款获得中国民航局适航认证的民族品牌轻型运动飞机，该机型荣获首届“中国优秀工业设计奖金奖”等荣誉，在同级别机型中国内市场占有率排名第一。液压静力压桩机市场占有率稳居全球第一。", "legal_representative": "付向东", "general_manager": "付向东", "secretary": "王剑", "established_date": 933177600000, "reg_asset": 1087212465.0, "staff_num": 5706, "telephone": "86-731-86407826", "postcode": "410100", "fax": "86-731-86407826", "email": "wangjian2@sunward.com.cn;yigm@sunward.com.cn;ir@sunward.com.cn", "org_website": "www.sunward.com.cn", "reg_address_cn": "湖南省长沙市长沙县星沙产业基地长龙街道凉塘东路1335号", "reg_address_en": "", "office_address_cn": "湖南省长沙市长沙县星沙产业基地长龙街道凉塘东路1335号", "office_address_en": "", "currency_encode": "019001", "currency": "CNY", "listed_date": 1166716800000, "provincial_name": "湖南省", "actual_controller": "广州市人民政府 (12.55%)", "classi_name": "地市国资控股", "pre_name_cn": "湖南山河智能机械股份有限公司", "chairman": "何清华", "executives_nums": 19, "actual_issue_vol": 33200000.0, "issue_price": 10.0, "actual_rc_net_amt": 316307425.0, "pe_after_issuing": 16.39, "online_success_rate_of_issue": 0.2042, "affiliate_industry": {"ind_code": "BK0018", "ind_name": "专用设备"}}