{"org_id": "01000928", "org_name_cn": "中钢国际工程技术股份有限公司", "org_short_name_cn": "中钢国际", "org_name_en": "Sinosteel Engineering & Technology Co.,Ltd.", "org_short_name_en": "SINOSTEEL ENTEC", "main_operation_business": "工程总承包为主的工程技术服务业务、以机电设备及备品备件集成供应为主的国内外贸易业务和以工程设计、咨询为主的服务业务。", "operating_scope": "　　冶金工程总承包；矿业工程总承包；电力工程总承包；化工工程总承包；环保工程设计、施工；建筑工程总承包；建筑装修装饰工程、建筑工程监理；机电设备安装工程；物业服务（以上各项均凭资质证书经营）；机械设备、交通运输设备、钢结构、电子产品、通信设备及以上项目零配件、仪器仪表、建材、化工产品（不含危险化学品）、焦炭、矿石、橡胶及制品、金属材料、汽车配件、工程机械经销；设备招标、代理；家具批发零售、房屋租赁；成套工程工艺及设备、自动化系统及液压系统设计；计算机软件开发；冶金技术服务；环保和节能技术及产品的研究开发、环境污染治理设施的专业化管理。（依法须经批准的项目，经相关部门批准后方可开展经营活动）。", "district_encode": "220202", "org_cn_introduction": "中钢国际工程技术股份有限公司主营业务是工程总承包为主的工程技术服务业务、以机电设备及备品备件集成供应为主的国内外贸易业务和以工程设计、咨询为主的服务业务。主要产品包括工程总承包、国内外贸易、服务收入。公司及所属企业已拥有冶金行业、建筑行业（建筑工程）、电子通信广电行业（通信铁塔）、环境工程（大气污染防治工程、固体废物处理处置工程、水污染防治工程）、市政行业（排水工程、环境卫生工程）甲级工程设计资质，钢铁、建筑、生态建设和环境工程专业甲级工程咨询资质，建筑工程施工、市政公用工程施工总承包壹级资质，特种设备安装改造维修许可（压力容器安装一级、工业管道GC2）、爆破作业单位许可（设计施工、安全评估、安全监理一级），对外承包工程、特种设备设计及检验检测、设备监理、设备成套、环境污染治理设施运营、安全评价机构甲级等齐全的行业资质，设有国家环境保护工业烟气控制工程技术中心、国家工业烟气除尘工程技术研究中心和“烟气多污染物控制技术与装备国家工程实验室”。", "legal_representative": "陆鹏程", "general_manager": "王建", "secretary": "袁陆生", "established_date": 733420800000, "reg_asset": 1256662942.0, "staff_num": 1944, "telephone": "86-10-62688099;86-10-62686202", "postcode": "100080;132002", "fax": "86-10-62686203", "email": "entec@mecc.sinosteel.com", "org_website": "mecc.sinosteel.com", "reg_address_cn": "吉林省吉林市昌邑区江湾路2号10楼1002、1003", "reg_address_en": "", "office_address_cn": "北京市海淀区海淀大街8号中钢国际广场26层,吉林省吉林市昌邑区江湾路2号世贸万锦10层", "office_address_en": "", "currency_encode": "019001", "currency": "CNY", "listed_date": 921168000000, "provincial_name": "吉林省", "actual_controller": "国务院国有资产监督管理委员会 (54.60%)", "classi_name": "央企国资控股", "pre_name_cn": "中钢集团吉林炭素股份有限公司", "chairman": "陆鹏程", "executives_nums": 17, "actual_issue_vol": 90000000.0, "issue_price": 6.28, "actual_rc_net_amt": 548100000.0, "pe_after_issuing": 14.8, "online_success_rate_of_issue": 0.6598, "affiliate_industry": {"ind_code": "BK0016", "ind_name": "建筑装饰"}}