{"org_id": "T000059611", "org_name_cn": "深圳市易尚展示股份有限公司", "org_short_name_cn": "易尚展示", "org_name_en": "Shenzhen Esun Display Co.,Ltd", "org_short_name_en": "ESUN", "main_operation_business": "终端展示、循环会展、虚拟展示、贸易服务及其他。", "operating_scope": "　　品牌展示策划、设计、推广服务；商业空间展示设计及建设；工程装饰、装修及工程施工；承办展览展示；数字多媒体的研发与应用；展览展示新材料的研发、推广应用；从事广告业务；国内贸易（法律、行政法规、国务院决定规定在登记前须经批准的项目除外）；货物进出口、技术进出口（法律、行政法规禁止的项目除外；法律、行政法规限制的项目须取得许可后方可经营）；兴办实业（具体项目另行申报）；创意产品设计、开发、销售；三维体验服务；3D打印服务；3D打印产品销售；信息系统集成服务；信息技术咨询、技术服务；计算机软件设计、应用、销售、技术开发、技术咨询、技术服务；集成电路设计、制造、应用、销售、技术服务；网络技术的研究、开发；3D数据处理和存储服务；3D数字内容服务（不含限制项目）；虚拟现实技术研发、应用；数字动漫制作；游戏软件设计制作。^展览展示道具的研发加工；展示及显示设备研发生产、数字多媒体的研发与应用、光电仪器研发生产；普通货运。数字化扫描成像服务以及相关设备研发、生产、销售。", "district_encode": "440306", "org_cn_introduction": "深圳市易尚展示股份有限公司主营业务由终端展示、循环会展、虚拟展示、贸易服务及其他业务五部分构成,是业内的\"品牌终端展示整体解决方案\"提供商.2009年,公司成为国美新活馆店面标准化展柜服务商,至今已为国美近300家店面提供了制作、安装和维修服务;因合作以来的优秀表现,2010年\"易尚展示\"被华为评为促销物料\"最佳合作响应奖\"供应商;2011年,公司随着海尔\"乡镇专卖店\"走进全国40000多个乡镇。", "legal_representative": "刘梦龙", "general_manager": "刘梦龙", "secretary": "陈焕洪", "established_date": 1083081600000, "reg_asset": 154529613.0, "staff_num": 666, "telephone": "86-755-23280085", "postcode": "518101", "fax": "86-755-83830798", "email": "chenhh@es-display.com;liukk@es-display.com", "org_website": "www.es-display.com", "reg_address_cn": "广东省深圳市宝安区新安街道海旺社区中心区甲岸南路易尚科技创意大厦二十三层", "reg_address_en": "", "office_address_cn": "广东省深圳市宝安区新安街道海旺社区中心区甲岸南路易尚科技创意大厦二十三层", "office_address_en": "", "currency_encode": "019001", "currency": "CNY", "listed_date": 1429804800000, "provincial_name": "广东省", "actual_controller": "刘梦龙 (20.87%)", "classi_name": "民营企业", "pre_name_cn": null, "chairman": "刘梦龙", "executives_nums": 13, "actual_issue_vol": 17560000.0, "issue_price": 10.48, "actual_rc_net_amt": 154968900.0, "pe_after_issuing": 22.98, "online_success_rate_of_issue": 0.33867889, "affiliate_industry": {"ind_code": "BK0039", "ind_name": "家用轻工"}}