{"org_id": "01000505", "org_name_cn": "海南京粮控股股份有限公司", "org_short_name_cn": "京粮控股", "org_name_en": "Hainan Jingliang Holdings Co., Ltd.", "org_short_name_en": "", "main_operation_business": "油脂油料加工销售及贸易和食品制造。", "operating_scope": "　　食品、饮料、油脂、油料及其副产品、植物蛋白及其制品、有机肥料、微生物肥料、农业肥料的生产销售；土地整理、土壤修复；农业综合种植开发、畜牧及水产养殖业，农业器械的生产和销售；计算机网络技术、通讯项目投资，高新技术产品研制和开发应用；环保项目投资及咨询；动漫、平面设计；货物及技术进出口贸易；自有房屋的租赁。（一般经营项目自主经营，许可经营项目凭相关许可证或者批准文件经营）（依法须经批准的项目，经相关部门批准后方可开展经营活动。）", "district_encode": "460106", "org_cn_introduction": "海南京粮控股股份有限公司主营业务为油脂油料加工销售及贸易和食品制造。油脂油料加工及贸易业务主要集中在京津冀区域，品牌包括“古船”、“绿宝”、“古币”、“火鸟”，主要产品有大豆油、菜籽油、葵花籽油、香油、麻酱等。食品制造主要是指休闲食品、面包的研发、生产及销售，品牌包括“小王子”、“董小姐”、“坚强的土豆”、“古船”等，主要产品有薯片、糕点及面包。", "legal_representative": "李少陵", "general_manager": "王春立", "secretary": "关颖", "established_date": 574963200000, "reg_asset": 726950251.0, "staff_num": 2907, "telephone": "86-10-51672029;86-10-51672130", "postcode": "570125", "fax": "86-10-51672010", "email": "jlkg@vip.163.com;1124387865@qq.com;gaodeqiu_jl@163.com", "org_website": "", "reg_address_cn": "海南省海口市龙华区滨海大道珠江广场帝豪大厦29楼", "reg_address_en": "", "office_address_cn": "海南省海口市龙华区滨海大道珠江广场帝豪大厦29楼", "office_address_en": "", "currency_encode": "019001", "currency": "CNY", "listed_date": 724867200000, "provincial_name": "海南省", "actual_controller": "北京市人民政府国有资产监督管理委员会 (39.68%)", "classi_name": "省属国资控股", "pre_name_cn": "海南珠江控股股份有限公司", "chairman": "李少陵", "executives_nums": 13, "actual_issue_vol": 21086400.0, "issue_price": 1.0, "actual_rc_net_amt": 21086400.0, "pe_after_issuing": null, "online_success_rate_of_issue": null, "affiliate_industry": {"ind_code": "BK0003", "ind_name": "农产品加工"}}