{"org_id": "01000525", "org_name_cn": "南京红太阳股份有限公司", "org_short_name_cn": "红太阳", "org_name_en": "Nanjing Red Sun Co.,Ltd.", "org_short_name_en": "RED SUN", "main_operation_business": "原药和制剂产品的生产销售、化肥生态肥的销售。", "operating_scope": "　　农药生产(按《农药生产许可证》和《安全生产许可证》所列项目经营)、农药产品包装物的生产、销售(按《危险化学品包装物、容器生产企业定点证书》核定的定点生产范围经营);三药中间体及精细化工产品的生产、销售、技术咨询和服务;化肥经营;投资管理及咨询;自营和代理各类商品及技术的进出口业务(国家限定企业经营或禁止进出口的商品和技术除外)。消毒剂销售(不含危险化学品)(依法须经批准的项目,经相关部门批准后方可开展经营活动)。", "district_encode": "320118", "org_cn_introduction": "南京红太阳股份有限公司是一家致力于绿色生命科学产业以环保农药、动物营养及中间体为主业,以国际贸易、农资连锁、农村云商为支撑,集科研、制造、国际国内市场一体化的全产业链高新技术企业和高科技上市公司。目前,公司产品范围涵盖除草剂、杀虫剂、杀菌剂、动物营养及中间体等系列。公司自相关政府部门开展环境信用等级评价以来,已连续多年获得“环保诚信”企业(环境信用等级评价中最高荣誉),并先后荣获“荣获国家级绿色工厂”、“节能示范企业”和“节水型企业”等多项荣誉。", "legal_representative": "杨寿海", "general_manager": "赵富明", "secretary": "杨寿海(代)", "established_date": 676738800000, "reg_asset": 580772873.0, "staff_num": 3195, "telephone": "86-25-57883588", "postcode": "211300", "fax": "86-25-57886828", "email": "redsunir@163.com", "org_website": "www.chinaredsun.com", "reg_address_cn": "江苏省南京市高淳区桠溪镇东风路8号", "reg_address_en": "", "office_address_cn": "江苏省南京市高淳区经济开发区古檀大道18号", "office_address_en": "", "currency_encode": "019001", "currency": "CNY", "listed_date": 751737600000, "provincial_name": "江苏省", "actual_controller": "杨寿海 (25.56%)", "classi_name": "民营企业", "pre_name_cn": "南京天龙股份有限公司", "chairman": "杨寿海", "executives_nums": 17, "actual_issue_vol": 20000000.0, "issue_price": 2.68, "actual_rc_net_amt": 50740000.0, "pe_after_issuing": null, "online_success_rate_of_issue": null, "affiliate_industry": {"ind_code": "BK0009", "ind_name": "化学制品"}}