{"org_id": "01002726", "org_name_cn": "鲁泰纺织股份有限公司", "org_short_name_cn": "鲁泰纺织", "org_name_en": "Lu Thai Textile Co.,Ltd", "org_short_name_en": "LTTC", "main_operation_business": "生产销售中、高档衬衫用色织布面料、印染面料、成衣等产品。", "operating_scope": "　　纱线、面料、衬衫、西服、大衣等纺织品、服装及饰品的设计、研发、生产和销售；纺织品及服装检测；电子商务平台的技术开发、服务、咨询；机电产品的加工、销售；农产品收购；酒店、宾馆、餐饮、会议、培训等服务；自有房屋、土地租赁业务；非配额许可证管理，非专营商品的收购、销售。", "district_encode": "370303", "org_cn_introduction": "鲁泰纺织股份有限公司是一家经营纺织品的公司,其公司的主导产品为衬衣用色织布面料和衬衫等,该公司是具有棉花种植、纺纱、漂染、织布、整理、制衣综合垂直生产能力的纺织企业集团,世界产量最大的高档衬衣色织面料生产厂商。公司自1995年起先后通过了ISO9000质量管理体系、ISO14000环境管理体系、OHSAS18000职业健康安全管理体系、SA8000社会责任管理体系，2007年至今公司通过了WRAP：1999环球服装生产社会责任标准、STeP可持续纺织品生产、GOTS全球有机纺织品认证标准、GRS全球回收标准的认证以及CNAS国家实验室认可，实现了公司管理的国际化、标准化和规范化。　　公司作为纺织制造行业的优势企业，被中国印染行业协会评为“中国印染企业30强”，被中国企业文化研究会评为“十三五”中国企业文化建设优秀单位，并被中国纺织工业联合会、中国纺织职工思想政治工作研究会授予“全国纺织行业党建工作先进企业”称号。", "legal_representative": "刘子斌", "general_manager": "刘子斌", "secretary": "张克明", "established_date": 593107200000, "reg_asset": 882419921.9999999, "staff_num": 22583, "telephone": "86-533-5285166;86-533-5277008", "postcode": "255100", "fax": "86-533-5418805", "email": "wyzheng@lttc.com.cn;lttc@lttc.com.cn;likun@lttc.com.cn;zhangkeming@lttc.com.cn", "org_website": "www.lttc.com.cn", "reg_address_cn": "山东省淄博市张店区高新技术开发区鲁泰大道61号", "reg_address_en": "", "office_address_cn": "山东省淄博市淄川区松龄东路81号", "office_address_en": "", "currency_encode": "019001", "currency": "CNY", "listed_date": 977673600000, "provincial_name": "山东省", "actual_controller": "刘德铭 (3.34%)，刘子斌 (0.66%)", "classi_name": "民营企业", "pre_name_cn": null, "chairman": "刘子斌", "executives_nums": 26, "actual_issue_vol": 50000000.0, "issue_price": 17.8, "actual_rc_net_amt": 866700000.0, "pe_after_issuing": 43.42, "online_success_rate_of_issue": 6.7597, "affiliate_industry": {"ind_code": "BK0035", "ind_name": "纺织制造"}}