{"org_id": "T000027606", "org_name_cn": "卫宁健康科技集团股份有限公司", "org_short_name_cn": "卫宁健康", "org_name_en": "Winning Health Technology Group Co.,Ltd.", "org_short_name_en": "Winning Health", "main_operation_business": "医疗卫生领域应用软件的研究开发、销售和技术服务。", "operating_scope": "　　从事健康科技领域内的技术开发、技术转让、技术咨询、技术服务，医疗器械生产（II类6870影像档案传输、处理系统软件），医疗器械经营，实业投资，自有房屋租赁；计算机软件的开发、设计和制作，计算机软、硬件及辅助设备的销售，计算机网络信息系统集成的维护，并提供相关的技术咨询和技术服务。【依法须经批准的项目，经相关部门批准后方可开展经营活动】", "district_encode": "310115", "org_cn_introduction": "卫宁健康科技集团股份有限公司是一家以医疗卫生领域应用软件的研究开发、销售和技术服务为主,并为医疗卫生行业信息化提供整体解决方案的软件企业。业务覆盖智慧医院、区域卫生、基层卫生、公共卫生、医疗保险、健康服务等领域，是中国医疗健康信息行业具有竞争力的整体产品、 解决方案与服务供应商。公司服务的各类医疗卫生机构用户达6,000余家，其中包括400余家三级医院，用户遍布全国除台湾、香港、西藏以外的31个省市自治区及特别行政区，是同行业客户覆盖最广的公司之一。取得了国家ITSS云计算服务能力(私有云IaaS)贰级、ITSS云计算服务能力(SaaS)贰级标准符合性证书，更强调技术对业务的驱动与赋能，为医院提供全面创新和转型动力医疗联合体信息化建设；持续推进AI+医疗健康应用落地，卫宁健康AI骨龄检测产品在上海市儿童医院成功落地案例，在2019CHITEC会议上荣获国家卫健委“医疗健康人工智能应用落地30最佳案例”。", "legal_representative": "周炜", "general_manager": "王涛", "secretary": "靳茂", "established_date": 1081267200000, "reg_asset": 2142425644.0, "staff_num": 5294, "telephone": "86-21-80331033", "postcode": "200072", "fax": "86-21-80331001", "email": "wndsh@winning.com.cn", "org_website": "www.winning.com.cn", "reg_address_cn": "上海市浦东新区东育路255弄4号3楼B29", "reg_address_en": "", "office_address_cn": "上海市静安区寿阳路99弄9号卫宁健康大厦", "office_address_en": "", "currency_encode": "019001", "currency": "CNY", "listed_date": 1313596800000, "provincial_name": "上海市", "actual_controller": "周炜 (9.34%)，王英 (4.97%)", "classi_name": "民营企业", "pre_name_cn": "上海金仕达卫宁软件股份有限公司", "chairman": "周炜", "executives_nums": 12, "actual_issue_vol": 13500000.0, "issue_price": 27.5, "actual_rc_net_amt": 338979830.0, "pe_after_issuing": 43.65, "online_success_rate_of_issue": 0.57696484, "affiliate_industry": {"ind_code": "BK0063", "ind_name": "计算机应用"}}