{"org_id": "Q004113120", "org_name_cn": "浙江嘉益保温科技股份有限公司", "org_short_name_cn": "嘉益股份", "org_name_en": "Zhejiang Cayi Vacuum Container Co.,Ltd.", "org_short_name_en": "CAYI", "main_operation_business": "各种不同材质的饮品、食品容器的研发设计、生产与销售。", "operating_scope": "　　保温容器、不锈钢制品、日用塑料制品、家用电器、金属工艺品、日用玻璃制品、日用陶瓷制品、办公用品、金属制日用品的研发、制造、网上及实物现场销售；货物进出口，技术进出口。（依法须经批准的项目，经相关部门批准后方可开展经营活动）", "district_encode": "330723", "org_cn_introduction": "浙江嘉益保温科技股份有限公司的主营业务为各种不同材质的饮品、食品容器的研发设计、生产与销售。公司的主要产品包括不锈钢真空保温器皿（保温杯、保温瓶、焖烧罐、保温壶、智能杯等）、不锈钢器皿、塑料器皿（PP、AS、Tritan等材质）、玻璃器皿以及其他新材料的日用饮品、食品容器。", "legal_representative": "戚兴华", "general_manager": "朱中萍", "secretary": "金学军", "established_date": 1084291200000, "reg_asset": 100000000.0, "staff_num": 982, "telephone": "86-579-89075611", "postcode": "321200", "fax": "86-579-87950708", "email": "jinxuejun@cayigroup.com;zhudinghui@cayigroup.com", "org_website": "www.cayigroup.com", "reg_address_cn": "浙江省金华市武义县经济开发区白洋工业区", "reg_address_en": "", "office_address_cn": "浙江省金华市武义县经济开发区白洋工业区", "office_address_en": "", "currency_encode": "019001", "currency": "CNY", "listed_date": 1624550400000, "provincial_name": "浙江省", "actual_controller": "戚兴华 (34.65%)，陈曙光 (31.51%)", "classi_name": "民营企业", "pre_name_cn": null, "chairman": "戚兴华", "executives_nums": 13, "actual_issue_vol": 25000000.0, "issue_price": 7.81, "actual_rc_net_amt": 156046100.0, "pe_after_issuing": 14.98, "online_success_rate_of_issue": 0.01547474, "affiliate_industry": {"ind_code": "BK0039", "ind_name": "家用轻工"}}