{"org_id": "T000027404", "org_name_cn": "恒信东方文化股份有限公司", "org_short_name_cn": "恒信东方", "org_name_en": "Hengxin Shambala Culture Co.,Ltd.", "org_short_name_en": "HXDF", "main_operation_business": "CG及VR内容生产制作、儿童产业链开发运营及LBE(LocationBasedEntertainment)城市新娱乐、移动信息产品的销售与服务", "operating_scope": "　　组织文化艺术交流；动画设计；产品设计；版权贸易；设计、制作、代理、发布广告；软件开发；技术推广服务；技术进出口、货物进出口；企业管理咨询；出租商业用房；出租办公用房；销售机械设备、电子产品、办公用品、通讯设备、计算机软件及辅助设备、玩具、家用电器、文具、体育用品、日用品、化妆品；计算机系统服务；摄影服务；教育咨询（不含中介服务）；出版物批发；出版物零售；销售食品；经营电信业务；广播电视节目制作；工程设计。（市场主体依法自主选择经营项目，开展经营活动；出版物批发以及出版物批发。以及依法须经批准的项目，经相关部门批准后依批准的内容开展经营活动；不得从事国家和本市产业政策禁止和限制类项目的经营活动。）", "district_encode": "110101", "org_cn_introduction": "恒信东方文化股份有限公司是一家主要从事数字文化创意、内容生产与技术服务的公司。公司的主要产品有LBE城市新娱乐、CG/VR影像内容生产、儿童产业链开发运营、互联网视频应用产品及服务、移动信息产品销售与服务。公司为我国数字创意产业领军企业之一,CG及VR技术国内领先、国际先进。", "legal_representative": "王冰", "general_manager": "孟楠", "secretary": "宫泽茹", "established_date": 1004716800000, "reg_asset": 529157876.00000006, "staff_num": 702, "telephone": "86-10-88846823", "postcode": "100097", "fax": "86-10-88846699", "email": "office@hxgro.com", "org_website": "www.hxgro.com", "reg_address_cn": "北京市东城区藏经馆胡同2号3幢一层101", "reg_address_en": "", "office_address_cn": "北京市海淀区蓝靛厂南路牛顿办公区北区11层", "office_address_en": "", "currency_encode": "019001", "currency": "CNY", "listed_date": 1274284800000, "provincial_name": "北京市", "actual_controller": "孟宪民 (20.09%)", "classi_name": "民营企业", "pre_name_cn": "恒信移动商务股份有限公司", "chairman": "王冰", "executives_nums": 16, "actual_issue_vol": 17000000.0, "issue_price": 38.78, "actual_rc_net_amt": 613030000.0, "pe_after_issuing": 62.55, "online_success_rate_of_issue": 1.06758395, "affiliate_industry": {"ind_code": "BK0064", "ind_name": "传媒"}}