{"org_id": "Q0036E401D", "org_name_cn": "深圳市易瑞生物技术股份有限公司", "org_short_name_cn": "易瑞生物", "org_name_en": "Shenzhen Bioeasy Biotechnology Co.,Ltd.", "org_short_name_en": "Bioeasy", "main_operation_business": "食品安全精准快速检测产品的研发、生产、销售及相关服务。", "operating_scope": "　　生物制品的技术开发；实验室仪器设备、一类医疗器械的销售；机动车的销售；快速检测车的销售；洁净工程、实验室工程、建筑装修装饰工程、机电工程的设计及施工；软件的技术开发、批发与零售；食品安全咨询；国内贸易，货物及技术进出口。（法律、行政法规、国务院决定规定在登记前须经批准的项目除外）食品安全快速检测试剂、仪器设备的技术开发、生产与销售（不含医药产品及其它限制项目）；检测仪器设备租赁；体外诊断试剂的研发、生产与销售；动物诊断产品研发、生产、销售及技术服务；兽药生产、销售（凭许可证在核定期限内经营）。实验分析仪器的研发、生产与销售；食品安全检测；餐饮服务（职工内部食堂）", "district_encode": "440306", "org_cn_introduction": "深圳市易瑞生物技术股份有限公司的主营业务是食品安全精准快速检测产品的研发、生产、销售及相关服务。公司的主要产品有胶体金免疫层析试纸、酶联免疫（ELISA）试剂盒、理化试剂、荧光PCR试剂盒、核酸提取试剂盒、体外诊断快速检测（POCT）产品。公司及其产品曾获得“国家质量监督检验检疫总局‘科技兴检奖’（一等奖）”等荣誉称号。部分产品取得了欧盟CE认证、美国FDA认证、美国分析化学家协会（AOAC）认证等国际认证，是新西兰、白俄罗斯、法国、比利时、波兰、厄瓜多尔等国家认可的中国大陆快检产品。", "legal_representative": "卢和华", "general_manager": "卢和华", "secretary": "张煜堃", "established_date": 1185206400000, "reg_asset": 400860000.0, "staff_num": 476, "telephone": "86-755-27948546", "postcode": "518101", "fax": "86-755-27948417", "email": "security@bioeasy.com", "org_website": "www.bioeasy.com", "reg_address_cn": "广东省深圳市宝安区新安街道兴东社区留仙一路易瑞生物大厦101（整栋）", "reg_address_en": "", "office_address_cn": "广东省深圳市宝安区新安街道兴东社区留仙一路易瑞生物大厦101（整栋）", "office_address_en": "", "currency_encode": "019001", "currency": "CNY", "listed_date": 1612800000000, "provincial_name": "广东省", "actual_controller": "朱海 (38.99%)，王金玉 (26.43%)", "classi_name": "民营企业", "pre_name_cn": null, "chairman": "朱海", "executives_nums": 16, "actual_issue_vol": 40860000.0, "issue_price": 5.31, "actual_rc_net_amt": 175353300.00000003, "pe_after_issuing": 28.11, "online_success_rate_of_issue": 0.02034106, "affiliate_industry": {"ind_code": "BK0065", "ind_name": "综合"}}