{"org_id": "T000238228", "org_name_cn": "湖南九典制药股份有限公司", "org_short_name_cn": "九典制药", "org_name_en": "Hunan Jiudian Pharmaceutical Co.,Ltd.", "org_short_name_en": "", "main_operation_business": "医药产品的研发、生产和销售。", "operating_scope": "　　药品、二类医疗器械、消毒剂、化工产品、卫生用品、化妆品、保健品、保健食品、食品、特殊医学用途配方食品、特殊膳食食品、一类医疗器械、中医药、生物制品、植物提取物的研发；化学药品制剂、化学药品原料药、生物药品、消毒剂、卫生材料及医药用品、化工产品、食品添加剂、固体饮料的制造；药用辅料、一类医疗器械、二类医疗器械、中药提取物、中成药、生物制品、卫生用品、化妆品、特殊医学用途配方食品、特殊膳食食品、保健食品的生产；药品、医药原料、生物制品、一类医疗器械、二类医疗器械、消毒剂、植物提取物、医药辅料、保健品、化妆品及卫生用品、保健食品、食品、预包装食品、散装食品、特殊医学用途配方食品、特殊膳食食品、食品添加剂、化工产品的销售；中成药、中药饮片的批发；医疗用品及器材的零售；生物技术开发服务、咨询、交流服务、转让服务；中药饮片加工；药用辅料的技术研发、咨询、技术转让；医学研究和试验发展；科技文献服务；科技信息咨询服务；化学工程研究服务；机械设备租赁；房屋租赁；场地租赁；自营和代理各类商品及技术的进出口，但国家限定公司经营或禁止进出口的商品和技术除外。（依法须经批准的项目，经相关部门批准后方可开展经营活动）。", "district_encode": "430181", "org_cn_introduction": "湖南九典制药股份有限公司主营业务为医药产品的研发、生产和销售，产品主要包括药品制剂、原料药、药用辅料及植物提取物四大类别。公司奥硝唑、塞克硝唑、地红霉素、左羟丙哌嗪、盐酸左西替利嗪等原料药合成技术处于国内领先水平，主导产品洛索洛芬钠凝胶膏、盐酸左西替利嗪、奥硝唑、地红霉素等原料药及口服制剂市场份额位居行业前列。", "legal_representative": "朱志宏", "general_manager": "郑霞辉", "secretary": "曾蕾", "established_date": 979833600000, "reg_asset": 234680000.0, "staff_num": 1273, "telephone": "86-731-82831002", "postcode": "410205", "fax": "86-731-88220260", "email": "jiudianzhiyao@163.com", "org_website": "www.hnjiudian.com", "reg_address_cn": "湖南省长沙市浏阳市经济技术开发区健康大道1号", "reg_address_en": "", "office_address_cn": "湖南省长沙市岳麓区麓天路28号金瑞麓谷科技园A1栋", "office_address_en": "", "currency_encode": "019001", "currency": "CNY", "listed_date": 1507564800000, "provincial_name": "湖南省", "actual_controller": "朱志宏 (35.76%)", "classi_name": "民营企业", "pre_name_cn": "湖南九典制药有限公司", "chairman": "朱志宏", "executives_nums": 14, "actual_issue_vol": 29340000.0, "issue_price": 10.37, "actual_rc_net_amt": 268253800.0, "pe_after_issuing": 22.97, "online_success_rate_of_issue": 0.02567017, "affiliate_industry": {"ind_code": "BK0040", "ind_name": "化学制药"}}